{"version": 0.6, "generator": "Overpass API 0.7.62.10 2d4cfc48", "osm3s": {"timestamp_osm_base": "2026-03-05T00:13:57Z", "copyright": "The data included in this document is from www.openstreetmap.org. The data is made available under ODbL."}, "elements": [{"type": "node", "id": 152385877, "lat": 30.28026, "lon": -97.684509}, {"type": "node", "id": 152385879, "lat": 30.2804306, "lon": -97.6844305}, {"type": "node", "id": 152385885, "lat": 30.2811283, "lon": -97.684439}, {"type": "node", "id": 152385887, "lat": 30.2812796, "lon": -97.6843449}, {"type": "node", "id": 152389639, "lat": 30.2825443, "lon": -97.6872593}, {"type": "node", "id": 152389641, "lat": 30.2828056, "lon": -97.6856003}, {"type": "node", "id": 152389644, "lat": 30.2825218, "lon": -97.6847884}, {"type": "node", "id": 152389647, "lat": 30.2817729, "lon": -97.6832022}, {"type": "node", "id": 152420818, "lat": 30.2830508, "lon": -97.6893256, "tags": {"highway": "turning_circle"}}, {"type": "node", "id": 152420819, "lat": 30.2835985, "lon": -97.689387}, {"type": "node", "id": 152420820, "lat": 30.284089, "lon": -97.689691}, {"type": "node", "id": 152420822, "lat": 30.2847382, "lon": -97.6898415}, {"type": "node", "id": 152427076, "lat": 30.2808697, "lon": -97.6858396}, {"type": "node", "id": 152427078, "lat": 30.2796266, "lon": -97.6832017}, {"type": "node", "id": 152427080, "lat": 30.2793492, "lon": -97.6828834}, {"type": "node", "id": 152429782, "lat": 30.2785463, "lon": -97.6896094}, {"type": "node", "id": 152435078, "lat": 30.282918, "lon": -97.681406}, {"type": "node", "id": 152457399, "lat": 30.282382, "lon": -97.691001}, {"type": "node", "id": 152457403, "lat": 30.283089, "lon": -97.69115}, {"type": "node", "id": 152457405, "lat": 30.283863, "lon": -97.691334}, {"type": "node", "id": 152457407, "lat": 30.2844748, "lon": -97.6914653}, {"type": "node", "id": 152462131, "lat": 30.2837485, "lon": -97.6961444, "tags": {"highway": "traffic_signals"}}, {"type": "node", "id": 152472619, "lat": 30.2924555, "lon": -97.6892977}, {"type": "node", "id": 152487239, "lat": 30.28376, "lon": -97.69206, "tags": {"highway": "turning_circle"}}, {"type": "node", "id": 152491589, "lat": 30.283671, "lon": -97.689096, "tags": {"highway": "turning_circle"}}, {"type": "node", "id": 152519969, "lat": 30.280841, "lon": -97.688971, "tags": {"highway": "turning_circle"}}, {"type": "node", "id": 152519973, "lat": 30.281324, "lon": -97.689033}, {"type": "node", "id": 152537332, "lat": 30.2839679, "lon": -97.6857332}, {"type": "node", "id": 152537333, "lat": 30.2833045, "lon": -97.6842678}, {"type": "node", "id": 152537335, "lat": 30.2827267, "lon": -97.6830185}, {"type": "node", "id": 152537338, "lat": 30.2825662, "lon": -97.6828707}, {"type": "node", "id": 152545789, "lat": 30.2829904, "lon": -97.6917113, "tags": {"highway": "turning_circle"}}, {"type": "node", "id": 152551634, "lat": 30.28209, "lon": -97.692587, "tags": {"highway": "turning_circle"}}, {"type": "node", "id": 152551637, "lat": 30.2842319, "lon": -97.6930329}, {"type": "node", "id": 152551646, "lat": 30.2782101, "lon": -97.6917851}, {"type": "node", "id": 152551649, "lat": 30.281243, "lon": -97.6924117}, {"type": "node", "id": 152560601, "lat": 30.282646, "lon": -97.680843}, {"type": "node", "id": 152561885, "lat": 30.281038, "lon": -97.688078, "tags": {"highway": "turning_circle"}}, {"type": "node", "id": 152561886, "lat": 30.2815169, "lon": -97.6881734}, {"type": "node", "id": 152561888, "lat": 30.2829235, "lon": -97.6883833}, {"type": "node", "id": 152561890, "lat": 30.2833503, "lon": -97.6880494}, {"type": "node", "id": 152561892, "lat": 30.2836338, "lon": -97.6875801}, {"type": "node", "id": 152561894, "lat": 30.2847641, "lon": -97.6864761}, {"type": "node", "id": 152561896, "lat": 30.2852481, "lon": -97.6864822}, {"type": "node", "id": 152567200, "lat": 30.2840804, "lon": -97.6940097}, {"type": "node", "id": 152567202, "lat": 30.2846233, "lon": -97.690613}, {"type": "node", "id": 152567217, "lat": 30.2848742, "lon": -97.6889633}, {"type": "node", "id": 152567222, "lat": 30.2850538, "lon": -97.687772}, {"type": "node", "id": 152567229, "lat": 30.285397, "lon": -97.685534}, {"type": "node", "id": 152567233, "lat": 30.285537, "lon": -97.684611}, {"type": "node", "id": 152569571, "lat": 30.2811813, "lon": -97.687047, "tags": {"highway": "turning_circle"}}, {"type": "node", "id": 152569574, "lat": 30.28168, "lon": -97.687088}, {"type": "node", "id": 152573784, "lat": 30.2841514, "lon": -97.6837363}, {"type": "node", "id": 152573786, "lat": 30.283698, "lon": -97.683056}, {"type": "node", "id": 152573789, "lat": 30.282247, "lon": -97.680056}, {"type": "node", "id": 152580625, "lat": 30.28449, "lon": -97.68439}, {"type": "node", "id": 152598183, "lat": 30.2817389, "lon": -97.6853104}, {"type": "node", "id": 152598185, "lat": 30.2811117, "lon": -97.6837669}, {"type": "node", "id": 152604780, "lat": 30.2828464, "lon": -97.6872794}, {"type": "node", "id": 152604784, "lat": 30.284925, "lon": -97.685473}, {"type": "node", "id": 152605750, "lat": 30.2830283, "lon": -97.685591, "tags": {"highway": "turning_circle"}}, {"type": "node", "id": 152612003, "lat": 30.282466, "lon": -97.690539}, {"type": "node", "id": 152612009, "lat": 30.282624, "lon": -97.690332}, {"type": "node", "id": 152612023, "lat": 30.282895, "lon": -97.690253}, {"type": "node", "id": 152633408, "lat": 30.2797505, "lon": -97.6931709}, {"type": "node", "id": 152656937, "lat": 30.284334, "lon": -97.688152}, {"type": "node", "id": 152656939, "lat": 30.2846942, "lon": -97.68775}, {"type": "node", "id": 152680152, "lat": 30.2899384, "lon": -97.6935672}, {"type": "node", "id": 152680154, "lat": 30.2896555, "lon": -97.6927284}, {"type": "node", "id": 152680156, "lat": 30.2895208, "lon": -97.6920196}, {"type": "node", "id": 152680161, "lat": 30.2896184, "lon": -97.6910699}, {"type": "node", "id": 152680164, "lat": 30.2900045, "lon": -97.6902518}, {"type": "node", "id": 152680167, "lat": 30.290387, "lon": -97.6898128}, {"type": "node", "id": 152680170, "lat": 30.2908422, "lon": -97.6895071}, {"type": "node", "id": 152680173, "lat": 30.2911228, "lon": -97.6893951}, {"type": "node", "id": 152680175, "lat": 30.2916424, "lon": -97.6893011}, {"type": "node", "id": 152692901, "lat": 30.2818671, "lon": -97.6859707}, {"type": "node", "id": 152695034, "lat": 30.2780592, "lon": -97.6927586}, {"type": "node", "id": 152714071, "lat": 30.2844998, "lon": -97.6887858}, {"type": "node", "id": 152714074, "lat": 30.284391, "lon": -97.688517}, {"type": "node", "id": 152733019, "lat": 30.278364, "lon": -97.6907923, "tags": {"bus": "yes", "public_transport": "stop_position"}}, {"type": "node", "id": 340230063, "lat": 30.2901294, "lon": -97.6944373}, {"type": "node", "id": 2128194345, "lat": 30.2803964, "lon": -97.6861453}, {"type": "node", "id": 2128194350, "lat": 30.2793564, "lon": -97.6867891}, {"type": "node", "id": 2128194353, "lat": 30.2796996, "lon": -97.6865849}, {"type": "node", "id": 2337778500, "lat": 30.2839588, "lon": -97.683337}, {"type": "node", "id": 2337778502, "lat": 30.2843922, "lon": -97.684278}, {"type": "node", "id": 2337778505, "lat": 30.2845233, "lon": -97.6856154}, {"type": "node", "id": 2505319908, "lat": 30.2811068, "lon": -97.683917}, {"type": "node", "id": 2505319910, "lat": 30.2811485, "lon": -97.6840683}, {"type": "node", "id": 2505319917, "lat": 30.2818545, "lon": -97.6855682}, {"type": "node", "id": 2505319919, "lat": 30.2818851, "lon": -97.6857613}, {"type": "node", "id": 3010905014, "lat": 30.2815509, "lon": -97.6908368}, {"type": "node", "id": 3010905015, "lat": 30.2810812, "lon": -97.6934788}, {"type": "node", "id": 3010905016, "lat": 30.2814038, "lon": -97.6914207}, {"type": "node", "id": 3010905017, "lat": 30.2815618, "lon": -97.6902012}, {"type": "node", "id": 3010905018, "lat": 30.2816657, "lon": -97.6897337}, {"type": "node", "id": 3010905019, "lat": 30.281763, "lon": -97.6895138}, {"type": "node", "id": 3010905020, "lat": 30.2821752, "lon": -97.6890448}, {"type": "node", "id": 3010905021, "lat": 30.2823165, "lon": -97.6886892}, {"type": "node", "id": 3010905022, "lat": 30.2823715, "lon": -97.6883551}, {"type": "node", "id": 3120750271, "lat": 30.2814848, "lon": -97.6909052}, {"type": "node", "id": 3271280477, "lat": 30.2794913, "lon": -97.682995}, {"type": "node", "id": 3271280479, "lat": 30.2795427, "lon": -97.6830586}, {"type": "node", "id": 3271280481, "lat": 30.2795822, "lon": -97.6831181}, {"type": "node", "id": 3728486199, "lat": 30.2811813, "lon": -97.6890553}, {"type": "node", "id": 3728486200, "lat": 30.2812623, "lon": -97.6890609}, {"type": "node", "id": 3728486201, "lat": 30.2813209, "lon": -97.6870219}, {"type": "node", "id": 3728486202, "lat": 30.2813628, "lon": -97.6889911}, {"type": "node", "id": 3728486203, "lat": 30.2813936, "lon": -97.6889296}, {"type": "node", "id": 4065321296, "lat": 30.2895176, "lon": -97.6917996}, {"type": "node", "id": 4065321297, "lat": 30.2895234, "lon": -97.6916237}, {"type": "node", "id": 4065321299, "lat": 30.2895361, "lon": -97.6914764}, {"type": "node", "id": 4065321300, "lat": 30.2895454, "lon": -97.6922661}, {"type": "node", "id": 4065321301, "lat": 30.2895628, "lon": -97.6913072}, {"type": "node", "id": 4065321302, "lat": 30.2895894, "lon": -97.6925223}, {"type": "node", "id": 4065321304, "lat": 30.2896682, "lon": -97.6909132}, {"type": "node", "id": 4065321306, "lat": 30.28974, "lon": -97.6907212}, {"type": "node", "id": 4065321309, "lat": 30.2898596, "lon": -97.6904793}, {"type": "node", "id": 4065321315, "lat": 30.2900318, "lon": -97.6938822}, {"type": "node", "id": 4065321316, "lat": 30.2900897, "lon": -97.6941557}, {"type": "node", "id": 4065321319, "lat": 30.2901453, "lon": -97.6900654}, {"type": "node", "id": 4065321322, "lat": 30.290179, "lon": -97.6949802}, {"type": "node", "id": 4065321324, "lat": 30.2901815, "lon": -97.6952387}, {"type": "node", "id": 4065321325, "lat": 30.2902576, "lon": -97.6899422}, {"type": "node", "id": 4065321330, "lat": 30.2905645, "lon": -97.6896751}, {"type": "node", "id": 4065321338, "lat": 30.2907081, "lon": -97.6895855}, {"type": "node", "id": 4065321343, "lat": 30.2909953, "lon": -97.689442}, {"type": "node", "id": 4065321354, "lat": 30.2913276, "lon": -97.6893412}, {"type": "node", "id": 4065321357, "lat": 30.2914747, "lon": -97.6893159}, {"type": "node", "id": 4344925341, "lat": 30.2842523, "lon": -97.6928897}, {"type": "node", "id": 4344963415, "lat": 30.2857692, "lon": -97.683066}, {"type": "node", "id": 4590076890, "lat": 30.290171, "lon": -97.6948528}, {"type": "node", "id": 5923351242, "lat": 30.2815932, "lon": -97.6901562}, {"type": "node", "id": 5923351243, "lat": 30.2815145, "lon": -97.6902177}, {"type": "node", "id": 5940874704, "lat": 30.2845357, "lon": -97.6878995}, {"type": "node", "id": 5940874705, "lat": 30.2827526, "lon": -97.6884105}, {"type": "node", "id": 5940874706, "lat": 30.2827256, "lon": -97.6872992}, {"type": "node", "id": 5940874707, "lat": 30.2827808, "lon": -97.6902555}, {"type": "node", "id": 5940874708, "lat": 30.282529, "lon": -97.690417}, {"type": "node", "id": 5967438273, "lat": 30.2826414, "lon": -97.6829236}, {"type": "node", "id": 6422326504, "lat": 30.2850658, "lon": -97.6967113}, {"type": "node", "id": 6422326506, "lat": 30.2854501, "lon": -97.6955393, "tags": {"noexit": "yes"}}, {"type": "node", "id": 6422326507, "lat": 30.2846343, "lon": -97.6957054, "tags": {"noexit": "yes"}}, {"type": "node", "id": 6422326508, "lat": 30.285292, "lon": -97.6959996}, {"type": "node", "id": 6909094506, "lat": 30.2839936, "lon": -97.6945635}, {"type": "node", "id": 8189305702, "lat": 30.2857045, "lon": -97.6834968}, {"type": "node", "id": 8189305715, "lat": 30.2857585, "lon": -97.6831373}, {"type": "node", "id": 8888706347, "lat": 30.2901807, "lon": -97.6950918}, {"type": "node", "id": 8908362758, "lat": 30.285114, "lon": -97.6965587, "tags": {"direction": "backward", "highway": "stop", "stop": "minor"}}, {"type": "node", "id": 8908362759, "lat": 30.2851907, "lon": -97.695954, "tags": {"direction": "forward", "highway": "stop", "stop": "minor"}}, {"type": "node", "id": 8908525735, "lat": 30.2852178, "lon": -97.6959662, "tags": {"crossing": "unmarked", "crossing:markings": "no", "highway": "crossing"}}, {"type": "node", "id": 8908525739, "lat": 30.2851028, "lon": -97.6965921, "tags": {"crossing": "unmarked", "crossing:markings": "no", "highway": "crossing"}}, {"type": "node", "id": 8908525756, "lat": 30.2848303, "lon": -97.695793}, {"type": "node", "id": 10047320996, "lat": 30.2838309, "lon": -97.6956031}, {"type": "node", "id": 10198506706, "lat": 30.283228, "lon": -97.6938576}, {"type": "node", "id": 10198506707, "lat": 30.2823224, "lon": -97.6936945}, {"type": "node", "id": 10198506708, "lat": 30.2816918, "lon": -97.6935893}, {"type": "node", "id": 10768962560, "lat": 30.2839212, "lon": -97.6950262}, {"type": "node", "id": 11188232762, "lat": 30.2854382, "lon": -97.6845901, "tags": {"highway": "crossing"}}, {"type": "node", "id": 11188232763, "lat": 30.2853292, "lon": -97.6855252, "tags": {"highway": "crossing"}}, {"type": "node", "id": 11188232764, "lat": 30.2851803, "lon": -97.6864696, "tags": {"crossing": "unmarked", "crossing:markings": "no", "highway": "crossing"}}, {"type": "node", "id": 11188232765, "lat": 30.2849405, "lon": -97.6877478, "tags": {"crossing": "unmarked", "crossing:markings": "no", "highway": "crossing"}}, {"type": "node", "id": 11188232766, "lat": 30.2847566, "lon": -97.6889376, "tags": {"crossing": "unmarked", "crossing:island": "no", "crossing:markings": "no", "highway": "crossing", "tactile_paving": "yes"}}, {"type": "node", "id": 11188232767, "lat": 30.2846384, "lon": -97.6898234, "tags": {"crossing": "unmarked", "crossing:island": "no", "crossing:markings": "no", "highway": "crossing", "tactile_paving": "yes"}}, {"type": "node", "id": 11188232768, "lat": 30.2845392, "lon": -97.6905955, "tags": {"crossing": "unmarked", "crossing:island": "no", "crossing:markings": "no", "highway": "crossing", "tactile_paving": "yes"}}, {"type": "node", "id": 11188232769, "lat": 30.2843606, "lon": -97.6914417, "tags": {"crossing": "unmarked", "crossing:island": "no", "crossing:markings": "no", "highway": "crossing", "tactile_paving": "yes"}}, {"type": "node", "id": 11188232770, "lat": 30.2841294, "lon": -97.6930116, "tags": {"crossing": "unmarked", "crossing:island": "no", "crossing:markings": "no", "highway": "crossing", "tactile_paving": "yes"}}, {"type": "node", "id": 11188232771, "lat": 30.2839786, "lon": -97.6939915, "tags": {"crossing": "unmarked", "crossing:island": "no", "crossing:markings": "no", "highway": "crossing", "tactile_paving": "yes"}}, {"type": "node", "id": 11188232783, "lat": 30.2837599, "lon": -97.6960694, "tags": {"button_operated": "yes", "crossing": "traffic_signals", "crossing:island": "no", "highway": "crossing", "tactile_paving": "yes", "traffic_signals:sound": "no"}}, {"type": "node", "id": 11188286381, "lat": 30.284108, "lon": -97.683656, "tags": {"crossing": "unmarked", "crossing:markings": "no", "crossing:signals": "no", "highway": "crossing"}}, {"type": "node", "id": 11188286382, "lat": 30.2832788, "lon": -97.6842111, "tags": {"crossing": "unmarked", "crossing:markings": "no", "crossing:signals": "no", "highway": "crossing", "kerb": "lowered"}}, {"type": "node", "id": 11188286383, "lat": 30.2824958, "lon": -97.6847327, "tags": {"crossing": "unmarked", "crossing:markings": "no", "highway": "crossing"}}, {"type": "node", "id": 11188286384, "lat": 30.2817025, "lon": -97.6852338, "tags": {"crossing": "unmarked", "crossing:markings": "no", "highway": "crossing"}}, {"type": "node", "id": 11188299647, "lat": 30.2808392, "lon": -97.685773, "tags": {"highway": "crossing"}}, {"type": "node", "id": 11351551264, "lat": 30.2841836, "lon": -97.6838088, "tags": {"crossing": "unmarked", "crossing:markings": "no", "crossing:signals": "no", "highway": "crossing"}}, {"type": "node", "id": 11351599370, "lat": 30.2833483, "lon": -97.6843623, "tags": {"crossing": "uncontrolled", "crossing:markings": "yes", "crossing:signals": "no", "highway": "crossing"}}, {"type": "node", "id": 11577256178, "lat": 30.2794192, "lon": -97.6829384, "tags": {"crossing": "uncontrolled", "crossing:markings": "yes", "crossing:signals": "no", "highway": "crossing"}}, {"type": "node", "id": 11716877642, "lat": 30.2901677, "lon": -97.6948199, "tags": {"crossing": "uncontrolled", "crossing:island": "yes", "crossing:markings": "zebra", "highway": "crossing"}}, {"type": "node", "id": 11716877652, "lat": 30.283889, "lon": -97.6895722}, {"type": "node", "id": 11716877653, "lat": 30.2831456, "lon": -97.6893003}, {"type": "node", "id": 11716877654, "lat": 30.2838118, "lon": -97.6895071}, {"type": "node", "id": 11716877656, "lat": 30.2848548, "lon": -97.6877356}, {"type": "node", "id": 11716877657, "lat": 30.2847792, "lon": -97.6877254}, {"type": "node", "id": 11716877658, "lat": 30.2843155, "lon": -97.6882728}, {"type": "node", "id": 11716877659, "lat": 30.2846746, "lon": -97.6889183}, {"type": "node", "id": 11716877661, "lat": 30.2849734, "lon": -97.6864287}, {"type": "node", "id": 11716877664, "lat": 30.2848812, "lon": -97.6864247}, {"type": "node", "id": 11716877691, "lat": 30.2784382, "lon": -97.6908076, "tags": {"crossing": "unmarked", "crossing:markings": "no", "highway": "crossing"}}, {"type": "node", "id": 11716877697, "lat": 30.2786241, "lon": -97.6896247, "tags": {"crossing": "unmarked", "crossing:markings": "no", "highway": "crossing"}}, {"type": "node", "id": 11716877718, "lat": 30.2782813, "lon": -97.6917998, "tags": {"crossing": "unmarked", "crossing:markings": "no", "highway": "crossing"}}, {"type": "node", "id": 11716877726, "lat": 30.2781314, "lon": -97.6927762, "tags": {"crossing": "unmarked", "crossing:markings": "no", "highway": "crossing"}}, {"type": "node", "id": 12521265609, "lat": 30.2817511, "lon": -97.6852743}, {"type": "node", "id": 12521265610, "lat": 30.281849, "lon": -97.6852101}, {"type": "node", "id": 12521265611, "lat": 30.2819118, "lon": -97.6852024}, {"type": "node", "id": 12521265612, "lat": 30.2818733, "lon": -97.6852605}, {"type": "node", "id": 12521265613, "lat": 30.2817743, "lon": -97.6853209}, {"type": "node", "id": 12521265617, "lat": 30.2818072, "lon": -97.6853008, "tags": {"crossing": "uncontrolled", "highway": "crossing"}}, {"type": "node", "id": 12521265618, "lat": 30.2817849, "lon": -97.6852522, "tags": {"crossing": "uncontrolled", "highway": "crossing"}}, {"type": "node", "id": 12521265619, "lat": 30.2827882, "lon": -97.6854432}, {"type": "node", "id": 12521265620, "lat": 30.2827508, "lon": -97.6852984}, {"type": "node", "id": 12521265621, "lat": 30.2823519, "lon": -97.6849278}, {"type": "node", "id": 12521265622, "lat": 30.282391, "lon": -97.6848692}, {"type": "node", "id": 12521265623, "lat": 30.2826428, "lon": -97.6847126}, {"type": "node", "id": 12521265624, "lat": 30.2827122, "lon": -97.6847028}, {"type": "node", "id": 12521265625, "lat": 30.2826708, "lon": -97.6847654}, {"type": "node", "id": 12521265626, "lat": 30.2824184, "lon": -97.6849195}, {"type": "node", "id": 12521265630, "lat": 30.2825694, "lon": -97.6848943, "tags": {"crossing": "unmarked", "crossing:markings": "no", "highway": "crossing"}}, {"type": "node", "id": 12521265631, "lat": 30.2825837, "lon": -97.6847496, "tags": {"crossing": "uncontrolled", "highway": "crossing"}}, {"type": "node", "id": 12521265632, "lat": 30.2826079, "lon": -97.6848038, "tags": {"crossing": "uncontrolled", "highway": "crossing"}}, {"type": "node", "id": 12521265633, "lat": 30.2824551, "lon": -97.6848296, "tags": {"crossing": "uncontrolled", "highway": "crossing"}}, {"type": "node", "id": 12521265634, "lat": 30.2824799, "lon": -97.684882, "tags": {"crossing": "uncontrolled", "highway": "crossing"}}, {"type": "node", "id": 12521265635, "lat": 30.2831288, "lon": -97.6844203}, {"type": "node", "id": 12521265636, "lat": 30.2835014, "lon": -97.6841657}, {"type": "node", "id": 12521265637, "lat": 30.283171, "lon": -97.6843614}, {"type": "node", "id": 12521265638, "lat": 30.2834296, "lon": -97.684184}, {"type": "node", "id": 12521265639, "lat": 30.2831997, "lon": -97.6843413}, {"type": "node", "id": 12521265640, "lat": 30.2834544, "lon": -97.6842317}, {"type": "node", "id": 12521265641, "lat": 30.2831971, "lon": -97.6844084}, {"type": "node", "id": 12521265642, "lat": 30.283328, "lon": -97.6843185}, {"type": "node", "id": 12521265648, "lat": 30.2847718, "lon": -97.6833427}, {"type": "node", "id": 12521265649, "lat": 30.2825458, "lon": -97.6848418}, {"type": "node", "id": 12521265650, "lat": 30.2829503, "lon": -97.6856072}, {"type": "node", "id": 12521265651, "lat": 30.2829893, "lon": -97.6856043}, {"type": "node", "id": 12521265652, "lat": 30.2829698, "lon": -97.6856058}, {"type": "node", "id": 12521880461, "lat": 30.2790794, "lon": -97.6869673}, {"type": "node", "id": 12521880462, "lat": 30.2809567, "lon": -97.6857864}, {"type": "node", "id": 12521880463, "lat": 30.280811, "lon": -97.6858782}, {"type": "node", "id": 12521880464, "lat": 30.2817724, "lon": -97.6852604}, {"type": "node", "id": 12521880465, "lat": 30.2817941, "lon": -97.6853088}, {"type": "node", "id": 12521880466, "lat": 30.2816326, "lon": -97.6853751}, {"type": "node", "id": 12521880467, "lat": 30.282469, "lon": -97.684821}, {"type": "node", "id": 12521880468, "lat": 30.2824934, "lon": -97.6848738}, {"type": "node", "id": 12521880469, "lat": 30.2825936, "lon": -97.6847434}, {"type": "node", "id": 12521880470, "lat": 30.2826182, "lon": -97.6847975}, {"type": "node", "id": 12521880471, "lat": 30.2824684, "lon": -97.684889}, {"type": "node", "id": 12521880472, "lat": 30.2832229, "lon": -97.684325}, {"type": "node", "id": 12521880473, "lat": 30.2832456, "lon": -97.6843751}, {"type": "node", "id": 12521880474, "lat": 30.2833797, "lon": -97.6842174}, {"type": "node", "id": 12521880475, "lat": 30.2834044, "lon": -97.684266}, {"type": "node", "id": 12521880476, "lat": 30.2840761, "lon": -97.6837861}, {"type": "node", "id": 12521880477, "lat": 30.2842249, "lon": -97.6836897}, {"type": "node", "id": 12522121320, "lat": 30.2826659, "lon": -97.6872863}, {"type": "node", "id": 12522121321, "lat": 30.2827831, "lon": -97.6873042}, {"type": "node", "id": 12522121322, "lat": 30.2828171, "lon": -97.6872955}, {"type": "node", "id": 12522121323, "lat": 30.2828885, "lon": -97.6872298}, {"type": "node", "id": 12522121324, "lat": 30.2851375, "lon": -97.6854876}, {"type": "node", "id": 12522121325, "lat": 30.2850313, "lon": -97.685471}, {"type": "node", "id": 12522121326, "lat": 30.2847242, "lon": -97.6855443}, {"type": "node", "id": 12522121327, "lat": 30.284624, "lon": -97.685584}, {"type": "node", "id": 12522121328, "lat": 30.2843857, "lon": -97.6856361}, {"type": "node", "id": 12522121329, "lat": 30.284242, "lon": -97.6856387}, {"type": "node", "id": 12522121330, "lat": 30.2841177, "lon": -97.6856576}, {"type": "node", "id": 12522121331, "lat": 30.28404, "lon": -97.6856856}, {"type": "node", "id": 12522121332, "lat": 30.2839262, "lon": -97.685777}, {"type": "node", "id": 12522121333, "lat": 30.2838916, "lon": -97.6858232}, {"type": "node", "id": 12522121334, "lat": 30.2828395, "lon": -97.6884079}, {"type": "node", "id": 12522121335, "lat": 30.283034, "lon": -97.6883386}, {"type": "node", "id": 12522121336, "lat": 30.283157, "lon": -97.6882692}, {"type": "node", "id": 12522121337, "lat": 30.2832304, "lon": -97.6882044}, {"type": "node", "id": 12522121338, "lat": 30.2832937, "lon": -97.6881312}, {"type": "node", "id": 12522121339, "lat": 30.283411, "lon": -97.6879165}, {"type": "node", "id": 12522121340, "lat": 30.2834742, "lon": -97.6877901}, {"type": "node", "id": 12522121341, "lat": 30.283554, "lon": -97.6876805}, {"type": "node", "id": 12522121342, "lat": 30.2846031, "lon": -97.6888915}, {"type": "node", "id": 12522121343, "lat": 30.2845444, "lon": -97.688849}, {"type": "node", "id": 12522121344, "lat": 30.2843468, "lon": -97.6883993}, {"type": "node", "id": 12522121345, "lat": 30.2843197, "lon": -97.6882093}, {"type": "node", "id": 12522121346, "lat": 30.2846137, "lon": -97.6878194}, {"type": "node", "id": 12522121347, "lat": 30.2847352, "lon": -97.6877315}, {"type": "node", "id": 12522121348, "lat": 30.2822579, "lon": -97.6888817}, {"type": "node", "id": 12522121349, "lat": 30.2822922, "lon": -97.6887869}, {"type": "node", "id": 12522121350, "lat": 30.2822225, "lon": -97.6889634}, {"type": "node", "id": 12522121351, "lat": 30.2820497, "lon": -97.6892023}, {"type": "node", "id": 12522121352, "lat": 30.2818858, "lon": -97.689365}, {"type": "node", "id": 12522121353, "lat": 30.2817138, "lon": -97.6896144}, {"type": "node", "id": 12522121354, "lat": 30.2818228, "lon": -97.689434}, {"type": "node", "id": 12522121355, "lat": 30.2815781, "lon": -97.6901835}, {"type": "node", "id": 12522121356, "lat": 30.2816858, "lon": -97.689674}, {"type": "node", "id": 12522121357, "lat": 30.2815408, "lon": -97.6902177}, {"type": "node", "id": 12528069463, "lat": 30.2842123, "lon": -97.6931591, "tags": {"bus": "yes", "public_transport": "stop_position"}}, {"type": "node", "id": 12528069465, "lat": 30.2838117, "lon": -97.6957293, "tags": {"bus": "yes", "public_transport": "stop_position"}}, {"type": "node", "id": 12529242521, "lat": 30.284238, "lon": -97.6929899, "tags": {"bus": "yes", "public_transport": "stop_position"}}, {"type": "node", "id": 12529592902, "lat": 30.2901503, "lon": -97.6946459, "tags": {"bus": "yes", "public_transport": "stop_position"}}, {"type": "node", "id": 12529808784, "lat": 30.292219, "lon": -97.6892987, "tags": {"bus": "yes", "public_transport": "stop_position"}}, {"type": "node", "id": 12543889660, "lat": 30.2824024, "lon": -97.6848621, "tags": {"bus": "yes", "public_transport": "stop_position"}}, {"type": "node", "id": 12543889662, "lat": 30.2799211, "lon": -97.6864452, "tags": {"bus": "yes", "public_transport": "stop_position"}}, {"type": "node", "id": 12544930897, "lat": 30.2792445, "lon": -97.6868611, "tags": {"bus": "yes", "public_transport": "stop_position"}}, {"type": "node", "id": 12544930899, "lat": 30.2818525, "lon": -97.6852732, "tags": {"bus": "yes", "public_transport": "stop_position"}}, {"type": "node", "id": 12747585722, "lat": 30.2855543, "lon": -97.6844962}, {"type": "node", "id": 12747585727, "lat": 30.285613, "lon": -97.6841056}, {"type": "node", "id": 12747585728, "lat": 30.2853086, "lon": -97.6845605}, {"type": "node", "id": 12747585731, "lat": 30.2851327, "lon": -97.6845239}, {"type": "way", "id": 15375943, "nodes": [152385877, 152385879, 152385885, 152385887], "tags": {"highway": "residential", "name": "Penny Street", "tiger:cfcc": "A41", "tiger:county": "Travis, TX", "tiger:name_base": "Penny", "tiger:name_type": "St", "tiger:zip_left": "78721", "tiger:zip_right": "78721"}}, {"type": "way", "id": 15376469, "nodes": [152389639, 152389641, 12521265619, 12521265620, 12521265630, 12521265649], "tags": {"highway": "residential", "name": "Leslie Avenue", "tiger:cfcc": "A41", "tiger:county": "Travis, TX", "tiger:name_base": "Leslie", "tiger:name_type": "Ave", "tiger:reviewed": "no", "tiger:zip_left": "78721", "tiger:zip_right": "78721"}}, {"type": "way", "id": 15379666, "nodes": [152420818, 11716877653, 152420819, 11716877654, 11716877652, 152420820, 11188232767, 152420822], "tags": {"highway": "residential", "name": "Victoria Drive", "tiger:cfcc": "A41", "tiger:county": "Travis, TX", "tiger:name_base": "Victoria", "tiger:name_type": "Dr", "tiger:reviewed": "no", "tiger:zip_left": "78721", "tiger:zip_right": "78721"}}, {"type": "way", "id": 15380299, "nodes": [152427076, 11188299647, 152385877, 152427078, 3271280481, 3271280479, 3271280477, 11577256178, 152427080], "tags": {"highway": "residential", "name": "Ribbecke Avenue", "sidewalk": "separate", "tiger:cfcc": "A41", "tiger:county": "Travis, TX", "tiger:name_base": "Ribbecke", "tiger:name_type": "Ave", "tiger:reviewed": "no", "tiger:zip_left": "78721", "tiger:zip_right": "78721"}}, {"type": "way", "id": 15383243, "nodes": [152457399, 152457403, 152457405, 11188232769, 152457407], "tags": {"highway": "residential", "lane_markings": "no", "name": "Adriane Drive", "surface": "asphalt", "tiger:cfcc": "A41", "tiger:county": "Travis, TX", "tiger:name_base": "Adriane", "tiger:name_type": "Dr", "tiger:reviewed": "no", "tiger:zip_left": "78721", "tiger:zip_left_1": "78641", "tiger:zip_right": "78721"}}, {"type": "way", "id": 15385430, "nodes": [152487239, 152457405], "tags": {"highway": "residential", "lane_markings": "no", "name": "Carmel Drive", "odbl": "clean", "surface": "asphalt", "tiger:cfcc": "A41", "tiger:county": "Travis, TX", "tiger:name_base": "Carmel", "tiger:name_type": "Dr", "tiger:reviewed": "no", "tiger:separated": "no", "tiger:source": "tiger_import_dch_v0.6_20070830", "tiger:tlid": "63948022", "tiger:zip_left": "78721", "tiger:zip_right": "78721"}}, {"type": "way", "id": 15385759, "nodes": [152420819, 152491589], "tags": {"highway": "residential", "name": "Monticello Circle", "odbl": "clean", "tiger:cfcc": "A41", "tiger:county": "Travis, TX", "tiger:name_base": "Monticello", "tiger:name_type": "Cir", "tiger:reviewed": "no", "tiger:separated": "no", "tiger:source": "tiger_import_dch_v0.6_20070830", "tiger:tlid": "63951478", "tiger:zip_left": "78721", "tiger:zip_right": "78721"}}, {"type": "way", "id": 15388475, "nodes": [152519969, 3728486199, 3728486200, 152519973], "tags": {"highway": "residential", "name": "Waldorf Avenue", "tiger:cfcc": "A41", "tiger:county": "Travis, TX", "tiger:name_base": "Waldorf", "tiger:name_type": "Ave", "tiger:zip_left": "78721", "tiger:zip_right": "78721"}}, {"type": "way", "id": 15390449, "nodes": [152537332, 11351599370, 12521265642], "tags": {"highway": "residential", "name": "Kitty Avenue", "tiger:cfcc": "A41", "tiger:county": "Travis, TX", "tiger:name_base": "Kitty", "tiger:name_type": "Ave", "tiger:reviewed": "no", "tiger:zip_left": "78721", "tiger:zip_right": "78721"}}, {"type": "way", "id": 15391413, "nodes": [152545789, 152457403], "tags": {"highway": "residential", "lane_markings": "no", "name": "Chase Circle", "odbl": "clean", "surface": "asphalt", "tiger:cfcc": "A41", "tiger:county": "Travis, TX", "tiger:name_base": "Chase", "tiger:name_type": "Cir", "tiger:reviewed": "no", "tiger:separated": "no", "tiger:source": "tiger_import_dch_v0.6_20070830", "tiger:tlid": "63948026", "tiger:zip_left": "78721", "tiger:zip_right": "78721"}}, {"type": "way", "id": 15391955, "nodes": [152551634, 11188232770, 152551637], "tags": {"highway": "residential", "lane_markings": "no", "name": "Perez Street", "surface": "asphalt", "tiger:cfcc": "A41", "tiger:county": "Travis, TX", "tiger:name_base": "Perez", "tiger:name_type": "St", "tiger:reviewed": "no", "tiger:zip_left": "78721", "tiger:zip_right": "78721"}}, {"type": "way", "id": 15391957, "nodes": [152551646, 11716877718, 152551649], "tags": {"highway": "residential", "name": "Perez Street", "tiger:cfcc": "A41", "tiger:county": "Travis, TX", "tiger:name_base": "Perez", "tiger:name_type": "St", "tiger:reviewed": "no", "tiger:zip_left": "78721", "tiger:zip_right": "78721"}}, {"type": "way", "id": 15392998, "nodes": [152561885, 152561886, 3010905022, 5940874705, 12522121334, 152561888, 12522121335, 12522121336, 12522121337, 12522121338, 152561890, 12522121339, 12522121340, 12522121341, 152561892, 152561894, 11716877664, 11716877661, 11188232764, 152561896], "tags": {"highway": "residential", "name": "Astor Place", "tiger:cfcc": "A41", "tiger:county": "Travis, TX", "tiger:name_base": "Astor", "tiger:name_type": "Pl", "tiger:reviewed": "no", "tiger:zip_left": "78721", "tiger:zip_right": "78721"}}, {"type": "way", "id": 15393558, "nodes": [152569571, 3728486201, 152569574], "tags": {"highway": "residential", "name": "Marcus Place", "tiger:cfcc": "A41", "tiger:county": "Travis, TX", "tiger:name_base": "Marcus", "tiger:name_type": "Pl", "tiger:zip_left": "78721", "tiger:zip_right": "78721"}}, {"type": "way", "id": 15393947, "nodes": [152573784, 11188286381, 2337778500, 152573786, 152435078, 152560601, 152573789], "tags": {"highway": "residential", "name": "Bandera Road", "tiger:cfcc": "A41", "tiger:county": "Travis, TX", "tiger:name_base": "Bandera", "tiger:name_type": "Rd", "tiger:reviewed": "no", "tiger:zip_left": "78721", "tiger:zip_right": "78721"}}, {"type": "way", "id": 15394506, "nodes": [152573784, 11351551264, 2337778502, 152580625, 12747585731, 12747585728, 11188232762, 152567233], "tags": {"highway": "residential", "name": "Overhill Drive", "tiger:cfcc": "A41", "tiger:county": "Travis, TX", "tiger:name_base": "Overhill", "tiger:name_type": "Dr", "tiger:reviewed": "no", "tiger:zip_left": "78721", "tiger:zip_right": "78721"}}, {"type": "way", "id": 15396040, "nodes": [152598183, 11188286384, 152385887, 2505319910, 2505319908, 152598185], "tags": {"highway": "residential", "name": "Wally Avenue", "tiger:cfcc": "A41", "tiger:county": "Travis, TX", "tiger:name_base": "Wally", "tiger:name_type": "Ave", "tiger:zip_left": "78721", "tiger:zip_right": "78721"}}, {"type": "way", "id": 15396600, "nodes": [152389639, 12522121320, 5940874706, 12522121321, 12522121322, 152604780, 12522121323, 12522121333, 12522121332, 152537332, 12522121331, 12522121330, 12522121329, 12522121328, 2337778505, 12522121327, 12522121326, 152604784, 12522121325, 12522121324, 11188232763, 152567229], "tags": {"highway": "residential", "name": "Elmira Road", "tiger:cfcc": "A41", "tiger:county": "Travis, TX", "tiger:name_base": "Elmira", "tiger:name_type": "Rd", "tiger:reviewed": "no", "tiger:zip_left": "78721", "tiger:zip_right": "78721"}}, {"type": "way", "id": 15396668, "nodes": [152389641, 12521265650, 12521265652, 12521265651, 152605750], "tags": {"highway": "residential", "name": "Fairplay Court", "tiger:cfcc": "A41", "tiger:county": "Travis, TX", "tiger:name_base": "Fairplay", "tiger:name_type": "Ct", "tiger:reviewed": "no", "tiger:zip_left": "78721", "tiger:zip_right": "78721"}}, {"type": "way", "id": 15397300, "nodes": [152551634, 152457399, 152612003, 5940874708, 152612009, 5940874707, 152612023, 11188232768, 152567202], "tags": {"highway": "residential", "lane_markings": "no", "name": "J J Seabrook Drive", "surface": "asphalt", "tiger:cfcc": "A41", "tiger:county": "Travis, TX", "tiger:name_base": "J J Seabrook", "tiger:name_type": "Dr", "tiger:reviewed": "no", "tiger:zip_left": "78721", "tiger:zip_right": "78721"}}, {"type": "way", "id": 15401701, "nodes": [152656937, 5940874704, 12522121346, 152656939, 12522121347, 11716877657, 11716877656, 11188232765, 152567222], "tags": {"highway": "residential", "name": "Temple Drive", "tiger:cfcc": "A41", "tiger:county": "Travis, TX", "tiger:name_base": "Temple", "tiger:name_type": "Dr", "tiger:reviewed": "no", "tiger:zip_left": "78721", "tiger:zip_right": "78721"}}, {"type": "way", "id": 15405426, "nodes": [152519973, 3728486202, 3728486203, 152561886, 152569574, 152692901, 2505319919, 2505319917, 152598183], "tags": {"highway": "residential", "name": "Glomar Avenue", "tiger:cfcc": "A41", "tiger:county": "Travis, TX", "tiger:name_base": "Glomar", "tiger:name_type": "Ave", "tiger:zip_left": "78721", "tiger:zip_right": "78721"}}, {"type": "way", "id": 15405733, "nodes": [152695034, 11716877726, 152633408, 3010905015, 10198506708, 10198506707, 10198506706, 11188232771, 152567200], "tags": {"hgv": "no", "highway": "residential", "lane_markings": "no", "name": "Deloney Street", "surface": "asphalt", "tiger:cfcc": "A41", "tiger:county": "Travis, TX", "tiger:name_base": "Deloney", "tiger:name_type": "St"}}, {"type": "way", "id": 15407567, "nodes": [152567217, 11188232766, 11716877659, 12522121342, 12522121343, 152714071, 152714074, 12522121344, 11716877658, 12522121345, 152656937], "tags": {"highway": "residential", "lane_markings": "no", "name": "Wildrose Drive", "surface": "asphalt", "tiger:cfcc": "A41", "tiger:county": "Travis, TX", "tiger:name_base": "Wildrose", "tiger:name_type": "Dr", "tiger:reviewed": "no", "tiger:zip_left": "78721", "tiger:zip_right": "78721"}}, {"type": "way", "id": 204998706, "nodes": [12521880461, 12544930897, 2128194350, 2128194353, 12543889662, 2128194345, 12521880463], "tags": {"cycleway": "track", "cycleway:both:buffer": "yes", "cycleway:both:separation": "flex_post", "highway": "secondary", "lanes": "2", "maxspeed": "30 mph", "name": "Springdale Road", "sidewalk:left": "no", "sidewalk:right": "separate", "surface": "asphalt"}}, {"type": "way", "id": 297234962, "nodes": [152457399, 3010905014], "tags": {"highway": "residential", "name": "Adriane Drive"}}, {"type": "way", "id": 297234963, "nodes": [3010905014, 3120750271, 3010905016, 152551649, 3010905015], "tags": {"highway": "residential", "maxspeed": "25 mph", "name": "East 16th Street"}}, {"type": "way", "id": 297234965, "nodes": [3010905016, 11716877691, 152733019], "tags": {"highway": "residential", "name": "Luna Street"}}, {"type": "way", "id": 297234967, "nodes": [3010905017, 12522121355, 5923351242, 3010905018, 12522121356, 12522121353, 3010905019, 12522121354, 12522121352, 12522121351, 3010905020, 12522121350, 12522121348, 12522121349, 3010905021, 3010905022], "tags": {"highway": "residential", "name": "East 16th Street"}}, {"type": "way", "id": 297234970, "nodes": [3010905017, 12522121357, 5923351243, 11716877697, 152429782], "tags": {"highway": "residential", "name": "Cometa Street"}}, {"type": "way", "id": 297234971, "nodes": [3010905022, 152389639], "tags": {"highway": "residential", "name": "Leslie Avenue"}}, {"type": "way", "id": 436609424, "nodes": [4344925341, 152457407, 152567202, 152420822, 152567217, 152567222, 152561896, 152567229, 152567233, 12747585722, 12747585727, 8189305702, 8189305715, 4344963415], "tags": {"hgv": "yes", "highway": "primary", "name": "East Martin Luther King Junior Boulevard", "name:etymology:wikidata": "Q8027", "old_name": "19th Street (Old Magnolia Avenue)", "ref": "FM 969", "source:hgv": "TxDOT\u2019s Sign Guidelines and Applications Manual, Chapter 5, Section 6 Truck Routes https://onlinemanuals.txdot.gov/TxDOTOnlineManuals/TxDOTManuals/smk/truck_routes.htm", "surface": "asphalt"}}, {"type": "way", "id": 685346108, "nodes": [6422326504, 8908525739, 8908362758, 6422326508, 6422326506], "tags": {"highway": "residential", "lanes": "2", "name": "Clary Way"}}, {"type": "way", "id": 685346109, "nodes": [6422326507, 8908525756, 8908362759, 8908525735, 6422326508], "tags": {"highway": "residential", "lanes": "2", "name": "Turtle Spring Court"}}, {"type": "way", "id": 754047947, "nodes": [10047320996, 10768962560, 6909094506, 152567200, 12528069463, 152551637], "tags": {"cycleway:both": "lane", "cycleway:both:buffer": "yes", "hgv": "yes", "highway": "primary", "lanes": "5", "lanes:backward": "2", "lanes:both_ways": "1", "lanes:forward": "2", "name": "East Martin Luther King Junior Boulevard", "name:etymology:wikidata": "Q8027", "old_name": "19th Street (Old Magnolia Avenue)", "ref": "FM 969", "source:hgv": "TxDOT\u2019s Sign Guidelines and Applications Manual, Chapter 5, Section 6 Truck Routes https://onlinemanuals.txdot.gov/TxDOTOnlineManuals/TxDOTManuals/smk/truck_routes.htm", "surface": "asphalt", "turn:lanes:both_ways": "left"}}, {"type": "way", "id": 764462783, "nodes": [4065321324, 8888706347, 4065321322, 4590076890, 11716877642, 12529592902, 340230063, 4065321316, 4065321315, 152680152, 152680154, 4065321302, 4065321300, 152680156, 4065321296, 4065321297, 4065321299, 4065321301, 152680161, 4065321304, 4065321306, 4065321309, 152680164, 4065321319, 4065321325, 152680167, 4065321330, 4065321338, 152680170, 4065321343, 152680173, 4065321354, 4065321357, 152680175, 12529808784, 152472619], "tags": {"cycleway:both": "track", "highway": "secondary", "lanes": "2", "maxspeed": "40 mph", "name": "Manor Road", "name:pronunciation": "\u02c8me\u026an\u0259r ro\u028ad", "old_ref": "SH 20"}}, {"type": "way", "id": 1097283342, "nodes": [152551637, 12529242521, 4344925341], "tags": {"hgv": "yes", "highway": "primary", "lanes": "5", "lanes:backward": "2", "lanes:both_ways": "1", "lanes:forward": "2", "name": "East Martin Luther King Junior Boulevard", "name:etymology:wikidata": "Q8027", "old_name": "19th Street (Old Magnolia Avenue)", "ref": "FM 969", "source:hgv": "TxDOT\u2019s Sign Guidelines and Applications Manual, Chapter 5, Section 6 Truck Routes https://onlinemanuals.txdot.gov/TxDOTOnlineManuals/TxDOTManuals/smk/truck_routes.htm", "surface": "asphalt", "turn:lanes:both_ways": "left"}}, {"type": "way", "id": 1097283343, "nodes": [152462131, 11188232783, 12528069465, 10047320996], "tags": {"cycleway:both": "lane", "cycleway:both:buffer": "no", "hgv": "yes", "highway": "primary", "lanes": "5", "lanes:backward": "2", "lanes:both_ways": "1", "lanes:forward": "2", "name": "East Martin Luther King Junior Boulevard", "name:etymology:wikidata": "Q8027", "old_name": "19th Street (Old Magnolia Avenue)", "ref": "FM 969", "source:hgv": "TxDOT\u2019s Sign Guidelines and Applications Manual, Chapter 5, Section 6 Truck Routes https://onlinemanuals.txdot.gov/TxDOTOnlineManuals/TxDOTManuals/smk/truck_routes.htm", "surface": "asphalt", "turn:lanes:both_ways": "left"}}, {"type": "way", "id": 1353219379, "nodes": [12521880477, 12521265648], "tags": {"cycleway:both": "track", "cycleway:both:buffer": "yes", "highway": "secondary", "lanes": "2", "maxspeed": "30 mph", "name": "Springdale Road", "surface": "asphalt"}}, {"type": "way", "id": 1353219380, "nodes": [12521265611, 12521265612, 12544930899, 12521265617, 12521880465], "tags": {"cycleway:right": "track", "cycleway:right:buffer": "yes", "cycleway:right:separation": "no", "highway": "secondary", "lanes": "1", "maxspeed": "30 mph", "name": "Springdale Road", "oneway": "yes", "sidewalk:left": "no", "sidewalk:right": "separate", "surface": "asphalt"}}, {"type": "way", "id": 1353219383, "nodes": [12521880464, 12521265618, 12521265610, 12521265611], "tags": {"cycleway:right": "track", "cycleway:right:buffer": "yes", "cycleway:right:separation": "flex_post", "highway": "secondary", "lanes": "1", "maxspeed": "30 mph", "name": "Springdale Road", "oneway": "yes", "sidewalk:left": "no", "sidewalk:right": "separate", "surface": "asphalt"}}, {"type": "way", "id": 1353219385, "nodes": [12521265611, 12521265621], "tags": {"cycleway:both": "track", "cycleway:both:buffer": "yes", "cycleway:both:separation": "flex_post", "highway": "secondary", "lanes": "2", "maxspeed": "30 mph", "name": "Springdale Road", "sidewalk": "separate", "surface": "asphalt"}}, {"type": "way", "id": 1353219386, "nodes": [12521880467, 152389644], "tags": {"cycleway:right": "lane", "cycleway:right:buffer": "no", "highway": "secondary", "lanes": "1", "maxspeed": "30 mph", "name": "Springdale Road", "oneway": "yes", "surface": "asphalt"}}, {"type": "way", "id": 1353219387, "nodes": [12521880470, 12521265632, 12521265649], "tags": {"cycleway:right": "lane", "cycleway:right:buffer": "no", "highway": "secondary", "lanes": "1", "maxspeed": "30 mph", "name": "Springdale Road", "oneway": "yes", "surface": "asphalt"}}, {"type": "way", "id": 1353219391, "nodes": [12521265624, 12521265635], "tags": {"cycleway:both": "track", "cycleway:both:buffer": "yes", "highway": "secondary", "lanes": "2", "maxspeed": "30 mph", "name": "Springdale Road", "surface": "asphalt"}}, {"type": "way", "id": 1353219392, "nodes": [12521880472, 152537333], "tags": {"cycleway:right": "lane", "cycleway:right:buffer": "no", "highway": "secondary", "lanes": "1", "maxspeed": "30 mph", "name": "Springdale Road", "oneway": "yes", "surface": "asphalt"}}, {"type": "way", "id": 1353219393, "nodes": [12521880475, 12521265642], "tags": {"cycleway:right": "lane", "cycleway:right:buffer": "no", "highway": "secondary", "lanes": "1", "maxspeed": "30 mph", "name": "Springdale Road", "oneway": "yes", "surface": "asphalt"}}, {"type": "way", "id": 1353275054, "nodes": [12521880462, 12521880466], "tags": {"cycleway": "track", "cycleway:both:buffer": "yes", "cycleway:both:separation": "flex_post", "highway": "secondary", "lanes": "2", "maxspeed": "30 mph", "name": "Springdale Road", "sidewalk:left": "no", "sidewalk:right": "separate", "surface": "asphalt"}}, {"type": "way", "id": 1353275055, "nodes": [12521880463, 152427076, 12521880462], "tags": {"cycleway:left": "track", "cycleway:left:buffer": "yes", "cycleway:right": "lane", "cycleway:right:buffer": "no", "highway": "secondary", "lanes": "2", "maxspeed": "30 mph", "name": "Springdale Road", "sidewalk:left": "no", "sidewalk:right": "separate", "surface": "asphalt"}}, {"type": "way", "id": 1353275056, "nodes": [152598183, 12521265609, 12521880464], "tags": {"cycleway:right": "lane", "cycleway:right:buffer": "no", "highway": "secondary", "lanes": "1", "maxspeed": "30 mph", "name": "Springdale Road", "oneway": "yes", "sidewalk:left": "no", "sidewalk:right": "separate", "surface": "asphalt"}}, {"type": "way", "id": 1353275057, "nodes": [12521880465, 12521265613, 152598183], "tags": {"cycleway:right": "lane", "cycleway:right:buffer": "no", "highway": "secondary", "lanes": "1", "maxspeed": "30 mph", "name": "Springdale Road", "oneway": "yes", "sidewalk": "no", "surface": "asphalt"}}, {"type": "way", "id": 1353275058, "nodes": [12521880466, 152598183], "tags": {"cycleway": "lane", "cycleway:both:buffer": "no", "highway": "secondary", "lanes": "2", "maxspeed": "30 mph", "name": "Springdale Road", "sidewalk:left": "no", "sidewalk:right": "separate", "surface": "asphalt"}}, {"type": "way", "id": 1353275059, "nodes": [12521265621, 12521265622, 12543889660, 12521265633, 12521880467], "tags": {"cycleway:right": "track", "cycleway:right:buffer": "yes", "highway": "secondary", "lanes": "1", "maxspeed": "30 mph", "name": "Springdale Road", "oneway": "yes", "surface": "asphalt"}}, {"type": "way", "id": 1353275060, "nodes": [12521880468, 12521265634, 12521880471, 12521265626, 12521265621], "tags": {"cycleway:right": "track", "cycleway:right:buffer": "yes", "highway": "secondary", "lanes": "1", "maxspeed": "30 mph", "name": "Springdale Road", "oneway": "yes", "surface": "asphalt"}}, {"type": "way", "id": 1353275061, "nodes": [12521880469, 12521265623, 12521265624], "tags": {"cycleway:right": "track", "cycleway:right:buffer": "yes", "highway": "secondary", "lanes": "1", "maxspeed": "30 mph", "name": "Springdale Road", "oneway": "yes", "surface": "asphalt"}}, {"type": "way", "id": 1353275062, "nodes": [12521265624, 12521265625, 12521880470], "tags": {"cycleway:right": "track", "cycleway:right:buffer": "yes", "highway": "secondary", "lanes": "1", "maxspeed": "30 mph", "name": "Springdale Road", "oneway": "yes", "surface": "asphalt"}}, {"type": "way", "id": 1353275063, "nodes": [12521265635, 12521265637, 12521265639, 12521880472], "tags": {"cycleway:right": "track", "cycleway:right:buffer": "yes", "highway": "secondary", "lanes": "1", "maxspeed": "30 mph", "name": "Springdale Road", "oneway": "yes", "surface": "asphalt"}}, {"type": "way", "id": 1353275064, "nodes": [12521880473, 12521265641, 12521265635], "tags": {"cycleway:right": "track", "cycleway:right:buffer": "yes", "highway": "secondary", "lanes": "1", "maxspeed": "30 mph", "name": "Springdale Road", "oneway": "yes", "surface": "asphalt"}}, {"type": "way", "id": 1353275065, "nodes": [12521880474, 12521265638, 12521265636], "tags": {"cycleway:right": "track", "cycleway:right:buffer": "yes", "highway": "secondary", "lanes": "1", "maxspeed": "30 mph", "name": "Springdale Road", "oneway": "yes", "surface": "asphalt"}}, {"type": "way", "id": 1353275066, "nodes": [12521265636, 12521265640, 12521880475], "tags": {"cycleway:right": "track", "cycleway:right:buffer": "yes", "highway": "secondary", "lanes": "1", "maxspeed": "30 mph", "name": "Springdale Road", "oneway": "yes", "surface": "asphalt"}}, {"type": "way", "id": 1353275067, "nodes": [12521265636, 12521880476], "tags": {"cycleway:both": "track", "cycleway:both:buffer": "yes", "highway": "secondary", "lanes": "2", "maxspeed": "30 mph", "name": "Springdale Road", "surface": "asphalt"}}, {"type": "way", "id": 1353275068, "nodes": [12521880476, 152573784, 12521880477], "tags": {"cycleway:both": "lane", "cycleway:both:buffer": "no", "highway": "secondary", "lanes": "2", "maxspeed": "30 mph", "name": "Springdale Road", "surface": "asphalt"}}, {"type": "way", "id": 1353838561, "nodes": [12521265649, 12521880468], "tags": {"cycleway:right": "lane", "cycleway:right:buffer": "no", "highway": "secondary", "lanes": "1", "maxspeed": "30 mph", "name": "Springdale Road", "oneway": "yes", "surface": "asphalt"}}, {"type": "way", "id": 1353838562, "nodes": [12521265649, 152389644], "tags": {"highway": "residential", "name": "Leslie Avenue", "tiger:cfcc": "A41", "tiger:county": "Travis, TX", "tiger:name_base": "Leslie", "tiger:name_type": "Ave", "tiger:reviewed": "no", "tiger:zip_left": "78721", "tiger:zip_right": "78721"}}, {"type": "way", "id": 1353838563, "nodes": [152389644, 12521265631, 12521880469], "tags": {"cycleway:right": "lane", "cycleway:right:buffer": "no", "highway": "secondary", "lanes": "1", "maxspeed": "30 mph", "name": "Springdale Road", "oneway": "yes", "surface": "asphalt"}}, {"type": "way", "id": 1353838564, "nodes": [152389644, 11188286383, 152389647], "tags": {"highway": "residential", "name": "Leslie Avenue", "tiger:cfcc": "A41", "tiger:county": "Travis, TX", "tiger:name_base": "Leslie", "tiger:name_type": "Ave", "tiger:reviewed": "no", "tiger:zip_left": "78721", "tiger:zip_right": "78721"}}, {"type": "way", "id": 1353838565, "nodes": [12521265642, 12521880473], "tags": {"cycleway:right": "lane", "cycleway:right:buffer": "no", "highway": "secondary", "lanes": "1", "maxspeed": "30 mph", "name": "Springdale Road", "oneway": "yes", "surface": "asphalt"}}, {"type": "way", "id": 1353838566, "nodes": [12521265642, 152537333], "tags": {"highway": "residential", "name": "Kitty Avenue", "tiger:cfcc": "A41", "tiger:county": "Travis, TX", "tiger:name_base": "Kitty", "tiger:name_type": "Ave", "tiger:reviewed": "no", "tiger:zip_left": "78721", "tiger:zip_right": "78721"}}, {"type": "way", "id": 1353838567, "nodes": [152537333, 12521880474], "tags": {"cycleway:right": "lane", "cycleway:right:buffer": "no", "highway": "secondary", "lanes": "1", "maxspeed": "30 mph", "name": "Springdale Road", "oneway": "yes", "surface": "asphalt"}}, {"type": "way", "id": 1353838568, "nodes": [152537333, 11188286382, 152537335, 5967438273, 152537338], "tags": {"highway": "residential", "name": "Kitty Avenue", "tiger:cfcc": "A41", "tiger:county": "Travis, TX", "tiger:name_base": "Kitty", "tiger:name_type": "Ave", "tiger:reviewed": "no", "tiger:zip_left": "78721", "tiger:zip_right": "78721"}}]}